relate/bin/Relate
relate/bin/RelateCoalescentRate
relate/bin/RelateExtract
relate/bin/RelateFileFormats
relate/bin/RelateMutationRate
relate/bin/RelateSelection
relate/bin/RelateTreeView
relate/bin/Tests
relate/bin/libUnitTest.a
relate/bin/libgzstreamShared.dylib
relate/bin/libgzstreamStatic.a
relate/bin/libkastoreShared.dylib
relate/bin/libkastoreStatic.a
relate/bin/librelateShared.dylib
relate/bin/librelateStatic.a
relate/bin/libtskitStatic.a
relate/include/evaluate/CMakeLists.txt
relate/include/evaluate/coalescent_rate/CoalescentRateForSection.cpp
relate/include/evaluate/coalescent_rate/FinalizePopulationSize.cpp
relate/include/evaluate/coalescent_rate/ReEstimateBranchLengths.cpp
relate/include/evaluate/coalescent_rate/RelateCoalescentRate.cpp
relate/include/evaluate/coalescent_rate/SummarizeCoalescentRateForGenome.cpp
relate/include/evaluate/coalescent_rate/coal_tree.cpp
relate/include/evaluate/coalescent_rate/coal_tree.hpp
relate/include/evaluate/mutation_rate/AvgMutationRate.cpp
relate/include/evaluate/mutation_rate/RelateMutationRate.cpp
relate/include/evaluate/selection/RelateSelection.cpp
relate/include/extract/AncMutChunks.cpp
relate/include/extract/Annotate.cpp
relate/include/extract/CMakeLists.txt
relate/include/extract/Convert.cpp
relate/include/extract/CreateAncesTreeFileForSubpopulation.cpp
relate/include/extract/GetTreeOfInterest.cpp
relate/include/extract/RelateExtract.cpp
relate/include/extract/RemoveTreesWithFewMutations.cpp
relate/include/file_formats/CMakeLists.txt
relate/include/file_formats/ConvertToTreeSequence.cpp
relate/include/file_formats/FileFormats.cpp
relate/include/file_formats/RelateFileFormats.cpp
relate/include/file_formats/tskit/CMakeLists.txt
relate/include/file_formats/tskit/convert.c
relate/include/file_formats/tskit/convert.h
relate/include/file_formats/tskit/core.c
relate/include/file_formats/tskit/core.h
relate/include/file_formats/tskit/genotypes.c
relate/include/file_formats/tskit/genotypes.h
relatepy-0.1.0.dist-info/METADATA
relatepy-0.1.0.dist-info/WHEEL
relatepy-0.1.0.dist-info/top_level.txt
relatepy-0.1.0.dist-info/RECORD
