Metadata-Version: 2.1
Name: relatepy
Version: 0.1.0
Author-email: Tang Ziya <tcztzy@hotmail.com>
Requires-Dist: click (==8.1.3)
Requires-Dist: click-log (==0.4.0)
Requires-Dist: cython (==3.0.0a11)
